Quanthon/Models.py
Quanthon/__init__.py
Quanthon/algorithms.py
Quanthon/ansatzs.py
Quanthon/base.py
Quanthon/expectation.py
Quanthon/exponential.py
Quanthon/history.py
Quanthon/mappers.py
Quanthon/mappers_utils.py
Quanthon/noise.py
Quanthon/physics.py
Quanthon/ut_pyscf_mel.py
Quanthon/ut_qiskit_hamiltonian.py
Quanthon/ut_test_jw.py
Quanthon/utils.py
Quanthon-0.4.0.dist-info/LICENSE
Quanthon-0.4.0.dist-info/METADATA
Quanthon-0.4.0.dist-info/WHEEL
Quanthon-0.4.0.dist-info/top_level.txt
Quanthon-0.4.0.dist-info/RECORD
